pylint_beam/__init__.py
pylint_beam/checkers.py
pylint_beam-0.1.2.dist-info/METADATA
pylint_beam-0.1.2.dist-info/WHEEL
pylint_beam-0.1.2.dist-info/top_level.txt
pylint_beam-0.1.2.dist-info/RECORD
