Metadata-Version: 2.1
Name: pylint-beam
Version: 0.1.2
Summary: Pylint plugin for Apache Beam
Home-page: https://github.com/kvudata/pylint-beam
Author: Krishna Vudata
Author-email: kvudata@gmail.com
License: MIT
Requires-Python: >=3.7
